webpagebp/__init__.py
webpagebp/browsers.py
webpagebp/generic_browser/__init__.py
webpagebp/generic_browser/browser.py
webpagebp/generic_browser/old_browser.py
webpagebp/job.py
webpagebp/scrapers/__init__.py
webpagebp/scrapers/soup.py
webpagebp/selenium_driver/__init__.py
webpagebp/selenium_driver/drivers.py
webpagebp/selenium_driver/generic_driver.py
webpagebp/utils.py
webpagebp/webpage.py
webpagebp-0.1.5.dist-info/LICENSE
webpagebp-0.1.5.dist-info/METADATA
webpagebp-0.1.5.dist-info/WHEEL
webpagebp-0.1.5.dist-info/RECORD
