Metadata-Version: 2.1
Name: webpagebp
Version: 0.1.5
Summary: 
Author: Sergio Schmilovich
Author-email: sergio.schmilovich@gmail.com
Requires-Python: >=3.10,<4.0
Classifier: Programming Language :: Python :: 3
Classifier: Programming Language :: Python :: 3.10
Classifier: Programming Language :: Python :: 3.11
Requires-Dist: bs4 (>=0.0.1,<0.0.2)
Requires-Dist: pytest (>=7.4.0,<8.0.0)
Requires-Dist: selenium (>=4.10.0,<5.0.0)
Requires-Dist: webdriver-manager (>=4.0.0,<5.0.0)
